mandrill.py
mandrill-1.0.60.data/scripts/mandrill
mandrill-1.0.60.data/scripts/sendmail.mandrill
mandrill-1.0.60.dist-info/LICENSE
mandrill-1.0.60.dist-info/METADATA
mandrill-1.0.60.dist-info/WHEEL
mandrill-1.0.60.dist-info/top_level.txt
mandrill-1.0.60.dist-info/RECORD
