Metadata-Version: 2.1
Name: mandrill
Version: 1.0.60
Summary: Deprecated. Replaced by mailchimp-transactional - A CLI client and Python API library for the Mandrill email as a service platform.
Home-page: https://bitbucket.org/mailchimp/mandrill-api-python/
Author: Mandrill Devs
Author-email: community@mandrill.com
License: Apache-2.0
Keywords: mandrill email api
Platform: UNKNOWN
Classifier: Development Status :: 7 - Inactive
Classifier: Environment :: Console
Classifier: Intended Audience :: Developers
Classifier: Intended Audience :: System Administrators
Classifier: License :: OSI Approved :: Apache Software License
Classifier: Topic :: Communications :: Email
Requires-Dist: requests (>=0.13.2)
Requires-Dist: docopt (==0.4.0)
